oknlp/__init__.py
oknlp/auto_config/adaptive_batch_size.py
oknlp/auto_config/__init__.py
oknlp/auto_config/gpu_scheduler.py
oknlp/auto_config/get_provider.py
oknlp/algorithm/__init__.py
oknlp/algorithm/abc/batch_algorithm_client.py
oknlp/algorithm/abc/algorithm.py
oknlp/algorithm/abc/__init__.py
oknlp/algorithm/abc/batch_algorithm_server.py
oknlp/algorithm/abc/batch_algorithm.py
oknlp/algorithm/typing/__init__.py
oknlp/algorithm/typing/BaseTyping.py
oknlp/algorithm/typing/bert_typing/__init__.py
oknlp/algorithm/typing/bert_typing/BertTyping.py
oknlp/algorithm/cws/BaseCWS.py
oknlp/algorithm/cws/__init__.py
oknlp/algorithm/cws/thulac_cws/__init__.py
oknlp/algorithm/cws/thulac_cws/THUlacCWS.py
oknlp/algorithm/cws/bert_cws/BertCWS.py
oknlp/algorithm/cws/bert_cws/__init__.py
oknlp/algorithm/ner/__init__.py
oknlp/algorithm/ner/BaseNER.py
oknlp/algorithm/ner/bert_ner/__init__.py
oknlp/algorithm/ner/bert_ner/BertNER.py
oknlp/algorithm/postagging/__init__.py
oknlp/algorithm/postagging/BasePosTagging.py
oknlp/algorithm/postagging/bert_postagging/BertPosTagging.py
oknlp/algorithm/postagging/bert_postagging/__init__.py
oknlp/algorithm/postagging/bert_postagging/class_list.py
oknlp/_C/__init__.py
oknlp/_C/thulac.cpython-36m-x86_64-linux-gnu.so
oknlp/config/__init__.py
oknlp/config/config.py
oknlp/utils/format_output.py
oknlp/utils/keyword.py
oknlp/utils/__init__.py
oknlp/utils/process_io.py
oknlp/data/__init__.py
oknlp/data/data_loads.py
oknlp-0.0.5.dist-info/top_level.txt
oknlp-0.0.5.dist-info/WHEEL
oknlp-0.0.5.dist-info/LICENSE
oknlp-0.0.5.dist-info/METADATA
oknlp-0.0.5.dist-info/RECORD
