Metadata-Version: 2.1
Name: oknlp
Version: 0.0.5
Summary: OKNLP
Home-page: https://github.com/thunlp/ink
Author: THUNLP
Author-email: thunlp@gmail.com
License: UNKNOWN
Platform: UNKNOWN
Classifier: Programming Language :: Python :: 3
Classifier: License :: OSI Approved :: MIT License
Classifier: Operating System :: OS Independent
Requires-Python: >=3.6
License-File: LICENSE
Requires-Dist: PyYaml
Requires-Dist: transformers (>=4)
Requires-Dist: kara-storage
Requires-Dist: py3nvml
Provides-Extra: cpu
Requires-Dist: onnxruntime (==1.8.0) ; extra == 'cpu'
Provides-Extra: cu102
Requires-Dist: onnxruntime-gpu (==1.6.0) ; extra == 'cu102'
Provides-Extra: cu110
Requires-Dist: onnxruntime-gpu (==1.7.0) ; extra == 'cu110'
Provides-Extra: cu111
Requires-Dist: onnxruntime-gpu (==1.7.0) ; extra == 'cu111'
Provides-Extra: cu112
Requires-Dist: onnxruntime-gpu (==1.7.0) ; extra == 'cu112'
Provides-Extra: cu11x
Requires-Dist: onnxruntime-gpu (==1.7.0) ; extra == 'cu11x'
